padelpy/__init__.py
padelpy/functions.py
padelpy/version.py
padelpy/wrapper.py
padelpy/PaDEL-Descriptor/Descriptors.xls
padelpy/PaDEL-Descriptor/PaDEL-Descriptor.jar
padelpy/PaDEL-Descriptor/descriptors.xml
padelpy/PaDEL-Descriptor/lib/ambit2-base-2.4.7-SNAPSHOT.jar
padelpy/PaDEL-Descriptor/lib/ambit2-core-2.4.7-SNAPSHOT.jar
padelpy/PaDEL-Descriptor/lib/ambit2-smarts-2.4.7-SNAPSHOT.jar
padelpy/PaDEL-Descriptor/lib/appframework-1.0.3.jar
padelpy/PaDEL-Descriptor/lib/cdk-1.4.15.jar
padelpy/PaDEL-Descriptor/lib/commons-cli-1.2.jar
padelpy/PaDEL-Descriptor/lib/guava-17.0.jar
padelpy/PaDEL-Descriptor/lib/jama.jar
padelpy/PaDEL-Descriptor/lib/jgrapht-0.6.0.jar
padelpy/PaDEL-Descriptor/lib/l2fprod-common-all.jar
padelpy/PaDEL-Descriptor/lib/libPaDEL-Descriptor.jar
padelpy/PaDEL-Descriptor/lib/libPaDEL-Jobs.jar
padelpy/PaDEL-Descriptor/lib/libPaDEL.jar
padelpy/PaDEL-Descriptor/lib/swing-worker-1.1.jar
padelpy/PaDEL-Descriptor/lib/vecmath1.2-1.14.jar
padelpy/PaDEL-Descriptor/lib/xom-1.1.jar
padelpy/PaDEL-Descriptor/license/LICENSE.txt
padelpy/PaDEL-Descriptor/license/README - CDK
padelpy/PaDEL-Descriptor/license/lgpl-2.1.txt
padelpy/PaDEL-Descriptor/license/lgpl.license
padelpy-0.1.15.dist-info/LICENSE
padelpy-0.1.15.dist-info/METADATA
padelpy-0.1.15.dist-info/WHEEL
padelpy-0.1.15.dist-info/top_level.txt
padelpy-0.1.15.dist-info/RECORD
