Metadata-Version: 2.1
Name: padelpy
Version: 0.1.15
Summary: A Python wrapper for PaDEL-Descriptor software
Author-email: Travis Kessler <travis.j.kessler@gmail.com>
Project-URL: Homepage, https://github.com/ecrl/padelpy
Project-URL: Bug Tracker, https://github.com/ecrl/padelpy/issues
Classifier: Programming Language :: Python :: 3.11
Classifier: License :: OSI Approved :: MIT License
Classifier: Operating System :: OS Independent
Requires-Python: >=3.11
License-File: LICENSE
